README.rst
setup.cfg
setup.py
./__init__.py
./product.py
./product.xml
./shipment.xml
./stock.py
./tryton.cfg
./tests/__init__.py
./tests/test_shipment.py
./tests/test_views_depends.py
./view/shipment_in_form.xml
./view/template_form.xml
openlabs_stock_lot_serial.egg-info/PKG-INFO
openlabs_stock_lot_serial.egg-info/SOURCES.txt
openlabs_stock_lot_serial.egg-info/dependency_links.txt
openlabs_stock_lot_serial.egg-info/entry_points.txt
openlabs_stock_lot_serial.egg-info/not-zip-safe
openlabs_stock_lot_serial.egg-info/requires.txt
openlabs_stock_lot_serial.egg-info/top_level.txt