Metadata-Version: 1.1
Name: openlabs-stock-lot-serial
Version: 3.0.1.0dev2
Summary: Tryton module for serialized inventory control.
Home-page: http://www.openlabs.co.in
Author: Openlabs Technologies & consulting (P) Limited
Author-email: info@openlabs.co.in
License: 3-clause BSD
Platform: UNKNOWN
Classifier: Development Status :: 4 - Beta
Classifier: Environment :: Plugins
Classifier: Intended Audience :: Developers
Classifier: License :: OSI Approved :: BSD License
Classifier: Natural Language :: English
Classifier: Operating System :: OS Independent
Classifier: Programming Language :: Python
Classifier: Framework :: Tryton
Classifier: Topic :: Office/Business
